README.md
setup.py
soco_grpc/__init__.py
soco_grpc/grpc_test.py
soco_grpc/model.py
soco_grpc/plugins_pb2.py
soco_grpc/plugins_pb2_grpc.py
soco_grpc/server.py
soco_grpc/query_server/__init__.py
soco_grpc/query_server/app/__init__.py
soco_grpc/query_server/app/main.py
soco_grpc/query_server/app/server/__init__.py
soco_grpc/query_server/app/server/app.py
soco_grpc/query_server/app/server/models/__init__.py
soco_grpc/query_server/app/server/models/data_manager.py
soco_grpc/query_server/app/server/models/heartbeat.py
soco_grpc/query_server/app/server/routes/__init__.py
soco_grpc/query_server/app/server/routes/clip_encode.py
soco_grpc/query_server/app/server/routes/heartbeat.py
soco_grpc/query_server/app/server/routes/query_encoder.py
soco_search_library.egg-info/PKG-INFO
soco_search_library.egg-info/SOURCES.txt
soco_search_library.egg-info/dependency_links.txt
soco_search_library.egg-info/requires.txt
soco_search_library.egg-info/top_level.txt