Metadata-Version: 2.1
Name: soco-search-library
Version: 0.0.9
Summary: Soco search plugin helper
Home-page: https://www.soco.ai
Author: wangze
License: UNKNOWN
Platform: UNKNOWN
Classifier: Programming Language :: Python :: 3
Classifier: License :: Free for non-commercial use
Classifier: Operating System :: OS Independent
